locust_csv2openmetrics.py
locust_csv2openmetrics-1.0.0.dist-info/METADATA
locust_csv2openmetrics-1.0.0.dist-info/WHEEL
locust_csv2openmetrics-1.0.0.dist-info/entry_points.txt
locust_csv2openmetrics-1.0.0.dist-info/RECORD
