Metadata-Version: 2.1
Name: locust_csv2openmetrics
Version: 1.0.0
Summary: Console app and Python API for converting locust's load test CSV formatted reports into the OpenMetrics text format
License: BSD
Keywords: Locust,OpenMetrics
Author: 360dialog development team
Author-email: info@360dialog.com
Requires-Python: >=3.10.0,<4.0.0
Classifier: Development Status :: 5 - Production/Stable
Classifier: Intended Audience :: Developers
Classifier: License :: Other/Proprietary License
Classifier: Operating System :: OS Independent
Classifier: Programming Language :: Python :: 3
Classifier: Programming Language :: Python :: 3.10
Classifier: Programming Language :: Python :: 3.11
Classifier: Programming Language :: Python :: 3.12
Classifier: Topic :: File Formats
Classifier: Topic :: Software Development
Classifier: Topic :: Utilities
Requires-Dist: prometheus-client (>=0.17.0,<0.18.0)
